[{"_id":{"$oid":"5aa104e0f20e84e6104ced2f"},"id":"514683790","type":"add","username":"mashainlove","bio":"","followed_by":177,"mentions":["anj_i","mothclub","radalewis"],"hashtags":["girlwithapearlearring","getaway","bristol","banksy","london","walthamstowwetlands","walthamstow","adaytoremember","kewgardens","nofilter"]},{"_id":{"$oid":"5aa104e0f20e84e6104ced30"},"id":"513856698","type":"add","username":"captjoach","bio":"22 | Montréal | Rimouski\nInstitut maritime du Québec","followed_by":943,"mentions":["coraliemitchell","portmtl","institutmaritimeduquebec","lalande71","canard_volant","lebrunsimon"],"hashtags":["sailorlife","malfunction","cabine4","105mm","tb","gaspesie","piratehunting","zeladaboys","canadiancoastguard","michigan"]},{"_id":{"$oid":"5aa104e0f20e84e6104ced31"},"id":"51276642","type":"add","username":"rosevalery","bio":"\"And though she be but little,  she is fierce\"\n            \" Strong is beautiful\" ❤❤ ▪■-------■▪⚓  \n Future nurse that loves to lift 💪💉","followed_by":314,"mentions":["will_power500","octurtles","crunchgardengrove","girlswhopowerlift","bigwilly_86"],"hashtags":["fitness","deadlift","neversettle","momsthatlift","gainsville","nikeromaleos2","gymjunkie","stronger","strongwoman","fitandthick"]},{"_id":{"$oid":"5aa104e0f20e84e6104ced32"},"id":"511371138","type":"add","username":"lider_sport","bio":"Фитнес клуб / лечебная физкультура / фитнес диагностика / кабинет массажа.\nТРК \"Гранд Каньон\", 3 этаж, м.Пр.Просвещения\n☎️380-10-27","followed_by":1768,"mentions":["gmail.com","rlinenutrition","gendaikan","spochan_rus","ulyanov_sfera","cheatmeal.shop","vorobey7777","skokowaan","damaged_always"],"hashtags":["соревнования","лидерспорт","кроссфит","грандканьон","фитнесклуб","пауэрлифтинг","powerlifting","юрийбелкин","8","подарок"]},{"_id":{"$oid":"5aa104e0f20e84e6104ced33"},"id":"510815932","type":"add","username":"jo_bennett1","bio":"Lover of family, good food, fine wine, family adventures, Jess 🐾 and the beach.","followed_by":277,"mentions":["restaurantigni","gourmettraveller","mrsjonesthebaker","tasmanseasalt","bondiharvest","guy_turland","tasteorange","nik_to","butcherandthefarmer","annata_sydney"],"hashtags":["goroseville","yearofthedog🐶","freshwater","gqmoty","happyanniversay","afrtop100restaurants","thestarsydney","thestar","vivid","best"]},{"_id":{"$oid":"5aa104e0f20e84e6104ced34"},"id":"577203589","type":"add","username":"lakynirving","bio":"🌹 Makeup l Self taught l WLG NZ\n💌 Business inquiries email lakyn1@hotmail.co.uk or DM\n👻 lakyn_irving","followed_by":410,"mentions":["lillyghalichi","milanicosmetics","lafemmebeautynz","xobeautyshop","nyxcosmetics","lifeiswhatyoucakeit","nikitahhx","maybelline","thebalmnz","makeupwithjah"],"hashtags":["getaway","sunset","newzealand","ocean","swim","brandnewzealand","summer","newzealandpics","nz","purenewzealand"]},{"_id":{"$oid":"5aa104e0f20e84e6104ced35"},"id":"508462165","type":"add","username":"meggsdoh","bio":"","followed_by":224,"mentions":["reid","bozemansustainabuild","jwoinjh","prodohkids","reider40","holladizzzle"],"hashtags":["toyotatacoma","adventureamericas","beginningofanewera","imayhavecriedalittle","evolution","mrmacsawyer","montanababyteether","thankshoney","lazylakedays","teamamericaexpanded"]},{"_id":{"$oid":"5aa104e0f20e84e6104ced36"},"id":"50829719","type":"add","username":"lexlykrumbs","bio":"Roya❤🐼\n1966 CHEVY C20\nThe Meadows,\nNevada.","followed_by":3598,"mentions":["ryanwing68","silverleemshores","alexdoming0o","ashwing07","bryce_skok","justhuskiess","siberianhuskiesofinsta","josephhaefstattooer"],"hashtags":["redheadproblems","morphe","makeup","freshdye","happyvalentinesday","eyeshadow","colourpop","huskypuppy","redhusky","husky"]},{"_id":{"$oid":"5aa104e0f20e84e6104ced37"},"id":"507862807","type":"add","username":"rubenderubi","bio":"","followed_by":415,"mentions":["irene.garal","ignaciogoitia","gsuslost","theexvotos","victorioylucchino_oficial","marta.roverato"],"hashtags":["nieve","venecia","balcon","grancanal","italia","palazzocontarinidellefigure","canalgrande","venezia","perros","gondola"]},{"_id":{"$oid":"5aa104e0f20e84e6104ced38"},"id":"505891591","type":"add","username":"kimannrussell","bio":"Pro Enduro Racer for Juliana, Chris King, Giro, Dakine, Dumonde Tech, RE Sports Wellness, Gnarly Nutrition, Kate's Real Food. Pro whitewater kayaker.","followed_by":1799,"mentions":["evilbicycles","svenmartinphoto","factory_jim_","freeridemadeira","ewsmadeira","gorgebikemechanic","kimannrussell","santacruzbicycles","yakimaracks","scapegoat_tattoo"],"hashtags":["buzz","mattepunch","reserverims","strega","doyouevendriftbro","shebeast","gognarly","gojuliana","rockshox","meetthehardins"]},{"_id":{"$oid":"5aa104e0f20e84e6104ced39"},"id":"5043828434","type":"add","username":"bikettle","bio":"Indoor cycling , circuit and kettlebell boutique","followed_by":119,"mentions":[],"hashtags":["momlife","pedal","wow","strongwomen","ourtime","winner","cycle","wemadeit","workout","mirror"]},{"_id":{"$oid":"5aa104e0f20e84e6104ced3a"},"id":"49686101","type":"add","username":"theloyaltyclub","bio":"Premium brand crafted only for the LOYAL few! ♣️®","followed_by":12573,"mentions":["swaelee","takeitforwhatitsworth_","335mm","unclejxm","arebernard","theloyaltyclub.us","jimmyfallon","jadeaholic","bigbaldhead","iamcardib"],"hashtags":["theloyaltyclub"]},{"_id":{"$oid":"5aa104e0f20e84e6104ced3b"},"id":"4951362642","type":"add","username":"honeycaycay","bio":"Gotta risk it all, to win big. \n🇸🇷🇨🇳 sc: honeycaycay","followed_by":2033,"mentions":["kimonomandem26","kierarenes","sbmoneygang","deep0104","tissskempi","pietjubell_official","therealmocromaniac","bizzey","suzanneslegers","3robimayne"],"hashtags":["curls","almere","showtimegroup","clubcell","showtimexamjent","makeup","doseofcolors","halloween","curlyhair","desixkaty"]},{"_id":{"$oid":"5aa104e0f20e84e6104ced3c"},"id":"4940938422","type":"add","username":"hayleemkup","bio":"15 yo /// insta priv- @hayleeprivate.x /// normal insta- @hayleemcphee /// snapchat- @haylee-mcphee1 /// add me on all ;)","followed_by":8742,"mentions":["slayingsoph","s.h.a.n.i.a_k.i.n.g","napoleonperdis","makeupinspirationsbyrocio","nailsmakeupbyjen","hayleesmakeupstuff","leah_beauty_","faceofaustralia","colourpopcosmetics","make.up.vines"],"hashtags":["makeuplook","babymuaslay","eyeliner","contour","makeupartist","f4f","beautytips","beautyguru","makeuptutorial","lipstick"]},{"_id":{"$oid":"5aa104e0f20e84e6104ced3d"},"id":"4921172628","type":"add","username":"scraptut495","bio":"📎полный ассортимент в группе ВКонтакте, ссылка ниже👇 📎вопросы с Директ или WA 📞+79262709604📎г. Москва  https://vk.com/scraptut","followed_by":2853,"mentions":[],"hashtags":["scraptut495","вырубка","скрапбукинг","card","фотоальбомыручнойработы","scrap","нождлявырубки","скрапальбом","скрап","scrapbooking"]},{"_id":{"$oid":"5aa104e0f20e84e6104ced3e"},"id":"49008547","type":"add","username":"clay_pollioni","bio":"Inquires: sam@fordmodels.com","followed_by":10249,"mentions":["chizznizz44","eddyokinsky","smithiptics","dakinesurf","dhamsrif","julieragolia","redbull","fullnelson_photo","m__g__v","teddy_hadjimarkos"],"hashtags":["winterstormriley","newmibia","happyvalentinesdayeveryone","noelanistorm","njsurf","teamges","tidepods","tgif","friday","newborn"]},{"_id":{"$oid":"5aa104e0f20e84e6104ced3f"},"id":"4863056833","type":"add","username":"moderndayoutdoors","bio":"5 Guys with an obsession for the Wild - Sharing our journey through our lens | Hunting for the blue collar | Not your daddy's TV Show |","followed_by":442,"mentions":["cjbrannon41","jsscents","sethhedrick","eastonarchery","remington_sct","ragebroadheads","patricksmith2012","cjbrannon51","xpeditionarchery","buckmastersnation"],"hashtags":["letemknow","cutters","moderndayoutdoors","hardtimekennels","hounds","sow","havalon","farm","shag","decentpigpiece"]},{"_id":{"$oid":"5aa104e0f20e84e6104ced40"},"id":"483592571","type":"add","username":"cloverleaffarm","bio":"Athens weddings\nA Divine Event\nA stunning Athens Georgia venue that specializes and delivers southern class and elegance at every event.","followed_by":560,"mentions":["deltaspirit","8rock_well5","lacey_mac","saradharper","ellenmcknight","kelseymschmidt","misslindseyj","sixhearts","budandbloomathens","eurofloral"],"hashtags":["cloverleaffarm","athens","brides","georgiaweddings","southernbride","weddingvenue","my_athens","southerncharm","magicmoments","stopandsmelltheclover"]},{"_id":{"$oid":"5aa104e0f20e84e6104ced41"},"id":"4821726033","type":"add","username":"pacificryo","bio":"15370 Fairfield Ranch Rd. Ste. E Chino Hills Ca 91709","followed_by":273,"mentions":["coo0p","kingjayee1","pacificryo","man.of.triumph","lmcquay22"],"hashtags":["chinohills","track","cold","yoga","pacificryo","theprocess","soccer","fitness","normatec","cool"]},{"_id":{"$oid":"5aa104e0f20e84e6104ced42"},"id":"1342613015","type":"add","username":"eventsscope","bio":"Take part in an event for Scope to support disabled people and their families.","followed_by":392,"mentions":["danieltbyrne","simonwinston","londonmarathon","ahappypace","ironmantri","wimbledon","athletelab","ridelondon","instagram","scopecharity"],"hashtags":["inspirationsdinner","richardwhitehead","scope","happynewyear","inspirational","teamscope","jokeforscope","thankyou","callumhawkins","run"]},{"_id":{"$oid":"5aa104e0f20e84e6104ced43"},"id":"4466393312","type":"add","username":"tashacobbs_leonard_","bio":"\"God chose Tasha Cobbs\"\n'gifted from she was in her mama's womb'","followed_by":394,"mentions":["urbanskinrx","pastorbcobbs","blendedfamiliesrock","jjhairston","musikdr","thedenyque","jekalyncarr","tashacobbs","bowtyetrib","marandacurtis"],"hashtags":["tbt❤️","perfect","leonard","mommy","familyfirst","gorgeous","new","tashacobbs","teamfalcons","tbt"]},{"_id":{"$oid":"5aa104e0f20e84e6104ced44"},"id":"187234862","type":"add","username":"juanfra1312","bio":"Dejarse llevar, suena demasiado bien...","followed_by":2075,"mentions":["futbolemotion","fcbfemeni","rayo_femenino","balonmanoalcobendas","laiam7","repostapp","ellassonfutbol","juanfra1312","palomamarco","losada_vicky"],"hashtags":["capitana","rayofemenino","fútbolfemenino","ligaiberdrola","spfútbol","feliz2018","nobleza","coraje","valentía","teesperamos"]},{"_id":{"$oid":"5aa104e0f20e84e6104ced45"},"id":"2271721077","type":"add","username":"josh_haden","bio":"I play bass and sing for @spaintheband","followed_by":532,"mentions":["rarebirdlit","maxdax","jamesafenton","edgregor","jamboxjim","damonhuss","jetlahgistan","theofficialresidents","ll.haden","joelvirgram"],"hashtags":["mlkweekend","mlkday","mlk","charliehaden","ornettecoleman","freejazz","deadseascrolls","spaintheband","2008","liverecording"]},{"_id":{"$oid":"5aa104e0f20e84e6104ced46"},"id":"1749509704","type":"add","username":"bushido.code","bio":"Life Mastery for Athletes, Fighters, Entrepreneurs & Badasses! Get your copy of the Bushido Code Life Mastery System below 👇","followed_by":56156,"mentions":["ariasdavid","movement4success","nateslaco","slavagoloubov","joerogan","bushido.code","ray.ahn","bushido.body","deepakdayal","seanfinallyfit"],"hashtags":[]},{"_id":{"$oid":"5aa104e0f20e84e6104ced47"},"id":"22385389","type":"add","username":"high4this","bio":"multidimensional⠀⠀⠀⠀⠀⠀⠀⠀","followed_by":180085,"mentions":["elle_lamb","dvvinci","prettyboykills","kvngslay","_victim15","shareefmosby","jreinaa_"],"hashtags":["tb","tbt","5headbutnobodyaskedyou","fuckitmaskoff","maskoff","bossup","may11th"]},{"_id":{"$oid":"5aa104e0f20e84e6104ced48"},"id":"223646163","type":"add","username":"loucabletopping","bio":"","followed_by":143,"mentions":["stantopping","cocoandmilo16","beckyannajohn","christchurchprk","fragile_and_khalesi"],"hashtags":["bromance","upcycle","pallet","christmas","southislandfoodandwinefestival","gameon","daddyslittlelion","lions","all","hohoho"]},{"_id":{"$oid":"5aa104e0f20e84e6104ced49"},"id":"221659662","type":"add","username":"micbaxter","bio":"","followed_by":633,"mentions":["tanyasooki","cntechnology","pkassar","nicolepretorius","chadbax","rossbarry92","rallysjc","mattyfresh123","marcogstl","ben870"],"hashtags":["sexualharassment","timesup","womensmarchlondon","womensmarch","metoo","thefutureisfemale","sprintforher","tbt","ruins","sexualassault"]},{"_id":{"$oid":"5aa104e0f20e84e6104ced4a"},"id":"201092353","type":"add","username":"luptondylan","bio":"NASCAR Driver | CA Born and Raised | UNC Charlotte Graduate | Twitter @luptondylan","followed_by":1510,"mentions":["martinsville_speedway","baylupton","bkracing_2383","vorevegas","jgl_racing","fatalclothing","get_repost","disupdates","kansasspeedway","nascar"],"hashtags":["surf","nascar","tattoo","california","racing","fatalclothing","motorcycle","skate","fordracing","daytona"]},{"_id":{"$oid":"5aa104e0f20e84e6104ced4b"},"id":"9246476","type":"add","username":"paepaedararat","bio":"22, based in bangkok","followed_by":2941,"mentions":["toeynatwara","maukmoore","hughlaughtonscott","praewpatt","sandsandd","plengyoo","mhunoii3","pachr","bacc","siam"],"hashtags":["olympusmjuii","fuji200","paepaegraduation","superdoublehot","เรียนจบแล้ว","👉🏾","fujicolor200","vista200","part6","fashiondesign"]},{"_id":{"$oid":"5aa104e0f20e84e6104ced4c"},"id":"312508352","type":"add","username":"rayslof","bio":"nunca mais se deixe esquecer onde nasce e mora todo o amor","followed_by":1232,"mentions":["oculisclausis","juliacdotto","kamylabelli","cassiorddtz"],"hashtags":["nofilter","amoresaosmontes","teatroporquenao"]},{"_id":{"$oid":"5aa104e0f20e84e6104ced4d"},"id":"3543824860","type":"add","username":"houseworkpress","bio":"Is an independent Risograph print press, publishers and graphic design studio.","followed_by":1940,"mentions":["undimensioned1970","doingmedoingyou","houseworkpress","serpentineuk","eyecheng","blacktowerprojects","housework.press","orticashop","fruttagallery","union_pacific_london"],"hashtags":["laurenkeeley","riso","printmaking","risoprintpress","printisntdead","rp3700","risoprinter","risoprint","unionpacific","peopleofprint"]},{"_id":{"$oid":"5aa104e0f20e84e6104ced4e"},"id":"2207669281","type":"add","username":"jennifer_biondo_wellness","bio":"Mother, wife, hypnotherapist, masseuse & essential oil lover.The one thing that motivates me the most is my love of helping people! #essentialoils","followed_by":573,"mentions":["melomamaof4","tinarex","blaine_gray","coifsalon","marina_spence","peachy566","melanierosewilliams","nickidemus","liberatehollywood","sirikhalsa"],"hashtags":["2","1","ferrisbueller","doterramom","toddlerlife","wildorange4life","costumeparty","depth","open","geranium"]},{"_id":{"$oid":"5aa104e0f20e84e6104ced4f"},"id":"22064955","type":"add","username":"sylk_z","bio":"💦🌹🌹💦","followed_by":1594,"mentions":["nachotorrrres","outmagazine","johnny_knapp","matyldakrzykowski","brittneyread","topicalcream_magazine","athenatorri","materialfair","deligallery","8ballradio"],"hashtags":["haptictactics","eyetoeye","danielsander","antibodies","kerricelewis","michellesegre","rip","2018","prototypes","monarchs"]},{"_id":{"$oid":"5aa104e0f20e84e6104ced50"},"id":"415334024","type":"add","username":"neyqrau","bio":"","followed_by":148,"mentions":["mauritiusvisit"],"hashtags":["visitcph","littletilde","forgottengiants","godjul","oumeulbakkery","mattplusmarene","nofilter","indoorstreetfood"]},{"_id":{"$oid":"5aa104e0f20e84e6104ced51"},"id":"4472297937","type":"add","username":"markessickband","bio":"","followed_by":141,"mentions":[],"hashtags":["levystraps","dunloppicks","seymoreduncan","mogamicable","fender","daddario","snarktuner","stewmac","jennyssouthside"]},{"_id":{"$oid":"5aa104e0f20e84e6104ced52"},"id":"2178727","type":"add","username":"xmuchuan","bio":"","followed_by":3041,"mentions":["uepandaaa","keitakosoba"],"hashtags":["squirtlegang","squirtlesquad","广州gd","武汉周杰坤","东莞李钟瑞"]},{"_id":{"$oid":"5aa104e0f20e84e6104ced53"},"id":"145936647","type":"add","username":"jorjacarroll","bio":"","followed_by":890,"mentions":["queen_margherita","thassassin","nataliegauciofficial","carlybermes","aarongobby","ciarangribbin","jacksonccarroll","usernameratboy","brassmonkeycronulla","zoiheard"],"hashtags":["gnocchi","jackjohnson","operahouse","fabiosfirstgaytime","marriageequality","welldoneaustralia","lovewins","poser","awkwardarm","hbdbella"]},{"_id":{"$oid":"5aa104e0f20e84e6104ced54"},"id":"4016762548","type":"add","username":"tinleaffreshkitchen","bio":"Come visit us, Open Daily 11am – 9pm! Located at 6985 El Camino Real Suite 108 Carlsbad, CA 92009 in the Paseo Real Plaza","followed_by":276,"mentions":["sadierosebakingco","tencatsmama","sgpgirl","wine.n.dine.mi","coastal.native","cafevirtuoso","yelpnorthsandiego","beachplumkitchen"],"hashtags":["sandiego","tinleaf","sandiegorestaurant","tinleaffreshkitchen","sdfoodies","chocolatechipcookies","carlsbadeats","carlsbadfoodie","oceansidefood","sdfoodie"]},{"_id":{"$oid":"5aa104e0f20e84e6104ced55"},"id":"2154009778","type":"add","username":"ca_mariuccia","bio":"Albugnano (AT) Localitá Sant'Emiliano 2","followed_by":84,"mentions":[],"hashtags":["animali","fattoriadidattica","agriturismo","fattoria","tiaspettiamo","natura","sabato","cavalli","domenica","weekend"]},{"_id":{"$oid":"5aa104e0f20e84e6104ced56"},"id":"2222910133","type":"add","username":"bikedrinkbehappy","bio":"","followed_by":268,"mentions":["demondeacons","farmtofeet","ncaabasketball","loidanna","sblindsley","smilesformilesandmiles","ncstate","medicalaxioms","pennstatefball","doctorapetri"],"hashtags":["20thanniversary","biglebowski","dailycalm","shoshin","cycling","dadddyanddaughterpedicure","daddydaughtertime","mountairybreweries","mymantra","sheis22"]},{"_id":{"$oid":"5aa104e0f20e84e6104ced57"},"id":"53124473","type":"add","username":"amirahkassem","bio":"😋🍭🍰@FlourShop🦄✨💖","followed_by":16296,"mentions":["topshop","bybridges","thecut","vansgirls","meredithjenks","oscardelarenta","dxprutting","barneysny","darthlaura","alysonromanok"],"hashtags":["romirah","flourshop","rmine","nationalpizzaday","miamorettixisatapia","cakehugs","verawangxladuree","tbt","vanscustomculture","caratheunicorn"]},{"_id":{"$oid":"5aa104e0f20e84e6104ced58"},"id":"2142124648","type":"add","username":"fastford_official","bio":"🚘This is fastfords brand new Instagram 🎉\n🚘Give us a follow for a follow back \n🚘DM us your car for an instant feature \n🚘We hope you enjoy this page","followed_by":352,"mentions":["ssibert_43"],"hashtags":["focus","st","fastford","red","ford","racered","sierra","retro","l4l","flf"]},{"_id":{"$oid":"5aa104e0f20e84e6104ced59"},"id":"1238350104","type":"add","username":"themanexpo","bio":"If you've got a video/pic of you doing something BAD ASS, send it to us with your IG name. We may post it and give you a shout out.","followed_by":3101,"mentions":["sheldonsadler","jgilly17","t_ocd","smuggl1n","petesurfrider","joshadjutant","vertexsports","_cannon_17","michael__lweezie"],"hashtags":["aviation","allthingsman","rchobby","rcairplane","rcpilot","manexpo","loading","flipping","cleanandpress","breakingmuscle"]},{"_id":{"$oid":"5aa104e0f20e84e6104ced5a"},"id":"2137216307","type":"add","username":"nikarthur","bio":"Portraits of boys and girls","followed_by":1449,"mentions":["cotty","itsoliviasparks","claudiastevenbeauty"],"hashtags":["quietthechaos","agameoftones","pursuitofportraits","l0tsabraids","aovportraits","lightroom","agameofportraits","ftwotw","artofvisuals","liveauthentic"]},{"_id":{"$oid":"5aa104e0f20e84e6104ced5b"},"id":"2978125597","type":"add","username":"makeupbymcchicken","bio":"self-taught/obsessed MUA • bookings/promotions: makeupbymckayla@gmail.com • main: @69mcchicken69","followed_by":1751,"mentions":["com","gmail","benefitcosmetics","beccacosmetics","nicolelongberry","nyxcosmetics","lagirlcosmetics","gmail.com","lovelexphotography","anastasiabeverlyhills"],"hashtags":["morphe35b","mua","morphegirl","abhpomade","highlight","anastasiabeverlyhillscosmetics","undiscovered_muas","abh","anastasiabrows","morphe"]},{"_id":{"$oid":"5aa104e0f20e84e6104ced5c"},"id":"3544875691","type":"add","username":"cervejapantheon","bio":"\"A Cerveja Artesanal dos Deuses\"\n🔞🍻🍻\nCurta a Pantheon no Facebook.com/cervejas Pantheon","followed_by":2028,"mentions":["casa_plural","cervejasemcasa","aliancacomavida","italianasso","tatianeguerreiro","amordebazar","mayraamaro","eapsp","marciolasalvia","oliquidosagrado"],"hashtags":["acervejadosdeuses","mitologiagrega","cerveja","ipaday","sampabeer","weissbier","cervejaartesanal","cervejasespeciais","hophunters","sampa"]},{"_id":{"$oid":"5aa104e0f20e84e6104ced5d"},"id":"2118327799","type":"add","username":"kitchen.wizard","bio":"Katie & Ted and Ivy","followed_by":44,"mentions":["skiplicker666","caytiemac","combover83","nickmayes","redtempleprayer"],"hashtags":["merlin","naaaattt","ted","doombar"]},{"_id":{"$oid":"5aa104e0f20e84e6104ced5e"},"id":"4459747165","type":"add","username":"youarebeautiful1523","bio":"An Oluwasewasimilara initiative\nCreating a platform for ladies to learn.....sharing real life stories to transform the younger generation...","followed_by":240,"mentions":["ronkegiwa1","abiolanurtures","shoeachildnigeria","myfigure8ng","ibadantrainings","_sewasimilara","mf8hub","jakim.productions","shelearnshere","wtg_nigeria"],"hashtags":["lendalisteningear","helptheyoungergeneration","youarebeautiful","notoaddictions","ibadangirlssecondaryschooltour","notolesbianism","notosuicidalthoughts","notobodyshaming","notolowselfesteem","notodepression"]},{"_id":{"$oid":"5aa104e0f20e84e6104ced5f"},"id":"2102404442","type":"add","username":"mediterraneosorrento","bio":"Looking for something different for your holidays???  \nHotel Mediterraneo Sorrento\n#theplacetobe!!!","followed_by":1827,"mentions":["perrierjouet","vistaskybar","hotel","saturday","vista","mediterraneosorrento","mediterraneosorrento.com","lunareprojectofficial","feudidisangregorio","andrew_barbershop"],"hashtags":["mansworld","sorrento","sorrentocoast","italianstyle","passion","barbershop","selfcare","romanticspot","food","restaurant"]},{"_id":{"$oid":"5aa104e0f20e84e6104ced60"},"id":"282280027","type":"add","username":"maximilchenko","bio":"check my new project ↙️↙️↙️","followed_by":3680,"mentions":["micmagic.kz","real_scrip","hammali_","sayonaraboy","shtasya","bumagaz","vobakat","sparish_maxim","jaxybayeva.aidana","thetridcattri"],"hashtags":["билетнафедука","maqscover","coveralmaty","хлопьялетятнаверх","cover","скоро","maqs","music","repost","minimal"]},{"_id":{"$oid":"5aa104e0f20e84e6104ced61"},"id":"215443033","type":"add","username":"padawanyogini","bio":"Mother 👼\nYoga Instructor 100hr🕉\nAerial Instructor🎪\nSkydiving🛫\nCycling🚲\nSober💊🚫","followed_by":1033,"mentions":["vicaerial922_","wildmoonyoga","calamityjill21","chad_buehler_photography","nickdtattoos","jill.henshaw","rayofjoyphotography","zenrio_","liforme","jeannevergerjewelry"],"hashtags":["standingbalance","yogapants","instayoga","feeltheyogahigh","strength","igyoga","yoga","yogaoffthemat","tattooedyogi","woosterohio"]},{"_id":{"$oid":"5aa104e0f20e84e6104ced62"},"id":"257147471","type":"add","username":"prototyp_3","bio":"Models Agency. México City.","followed_by":571,"mentions":["jayandrade7","tanyusha_velichutina","juliayrenata","sandraweil","revista20s","modareforma","repostapp","miguelangelopes","voguemexico","fweekendmx"],"hashtags":["beautiful","prototyp3models","mexicanmodel","prototyp3","intown","model","méxico","girl","bookhernow","nuestrabelleza"]},{"_id":{"$oid":"5aa104e0f20e84e6104ced63"},"id":"209267046","type":"add","username":"coloradorockdiggingqueen","bio":"I love the Colorado land and all the secrets it holds! I love my weeners\nBonzai-5/2003\nSweet Lilly 4/2007\nBarney 9/2012\nwww.gofundme/helpBanditsMom","followed_by":3545,"mentions":["bushka_boo","karens_jellies_n_more","ali.cresswell","darling.dogs","4mykids1010","wee_knee_adventures","evilwienerjimmydean","ddtall82","ourdoghouse","itstarablack"],"hashtags":["lovemydoxie","wienerdog","twinbrogang","sausagedog","doxie_dogs","weiner","wiener","doxy_love","wieners","doxiesofinstagram"]},{"_id":{"$oid":"5aa104e0f20e84e6104ced64"},"id":"1717855191","type":"add","username":"tabithapaige","bio":"🌚🔮🌻🌲🦋🌙\n📍TX | @tabithapaige","followed_by":1979,"mentions":["bellabluenola","eileendelatorre","darth_alebau"],"hashtags":["greenlife","plantlife","humbleabode","greenery","magic","magicmonday","witchy","ekapadarajakapotasanaiv","engaged","isaidyes"]},{"_id":{"$oid":"5aa104e0f20e84e6104ced65"},"id":"302917825","type":"add","username":"bahlneha","bio":"Staring into Nothingness...♣♧ \n#foodie #adventureseeker #anxious #secretlypoet #beachnhills #workaholic #chocoholic \nDelhi|London|Bangalore|Toronto","followed_by":599,"mentions":["khush165","niveditacshenoy","cntower","ajwanipooja","lovetoronto","aeyybae","cntowertoronto","toronto","toronto_story","toronto_insta"],"hashtags":["toronto","midweekcatchup","missing","torontoinsta","torono_insta","torontomind","whereisthesnow","sunnyday","torontolife","toront_online"]},{"_id":{"$oid":"5aa104e0f20e84e6104ced66"},"id":"2090561523","type":"add","username":"evanmorgansphotography","bio":"I am a Brisbane based landscape / sea scape photographer who loves being out and about to record what i see!","followed_by":5016,"mentions":["_jeremyherbert_","bgoodphotos","brianbornstein","sam.ison.photos","cmac6248","jacquesvaphotography","vickijanefletcher","sharkbite_aus","focusaustralia"],"hashtags":["ig_australia","ig_color","thisisqueensland","theimaged","cruising_australia","mammatus","seeaustralia","flyingfox","longexpo_addiction","longexpoelite"]},{"_id":{"$oid":"5aa104e0f20e84e6104ced67"},"id":"185823472","type":"add","username":"fabsquared","bio":"Crazy-Kitten-Smile. A rolling stone gathers no moss... I rose from ashes, now I dance in fire✨Yes VEgan✌🏽","followed_by":1034,"mentions":["thisismylifegoodnbad","leosenzainstagram","valerialugoc","rototomsunsplash","antoniodjanikian","the.wailers","naeliasalas","ajnissly25","montalthrash","wopoilguapo"],"hashtags":["tbt","sunset","elmejoramigodewassy","skateboarding","rototomsunsplash","wassilyk","cuyagua","tb2012","internationalwomensday","apure"]},{"_id":{"$oid":"5aa104e0f20e84e6104ced68"},"id":"208004680","type":"add","username":"lrobitschek","bio":"Managing Partner, F&B: The NoMad Hotel. Bar Director Make it Nice Hospitality: Eleven Madison Park, NoMad and NoMad Bar","followed_by":7285,"mentions":["thesurflodge","macchu_pisco","aperolusa","absolutelyx","shakeshack","made_nice","get_repost","pietrocollina","empsummerhouse","barlabcocktails"],"hashtags":["nomadla","negroni","thenomad","nomadbar","celeryroot","empsummerhouse","empwinterhouse","makeitnice","birthday","elyx"]},{"_id":{"$oid":"5aa104e0f20e84e6104ced69"},"id":"3077639973","type":"add","username":"yeuxdemoi","bio":"🇫🇷🥐 ғrєncн ғor єyєѕ oғ мє\n✨ 📸 pυвlιѕнєd pнoтograpнєr and ѕтylιѕт \n📍🌍ѕaιnт loυιѕ, мo\n⬇️⬇️⬇️⬇️⬇️","followed_by":1169,"mentions":["redd818"],"hashtags":[]},{"_id":{"$oid":"5aa104e0f20e84e6104ced6a"},"id":"2038351708","type":"add","username":"sidorov_aleksandr23","bio":"⚫Основатель Мастерской Полезного Питания \n⚫Счастливый отец  \n⚫Сертифицированный тренер (FPA,LIFE FITNESS,TRX)","followed_by":411,"mentions":["atmosphere_fitness_33","centralcourt_moscow","dashafitnesbzik"],"hashtags":["фитнес","правильноепитание","зож","атмосфера","убабули","дача","лето","отдыхаем","ясоздаю","ясоздаюкоманду"]},{"_id":{"$oid":"5aa104e0f20e84e6104ced6b"},"id":"192297054","type":"add","username":"frigidaire","bio":"At Frigidaire®, we know the unique way you do things is what makes your home awesome. So we design products to help you run your home, your way.","followed_by":3922,"mentions":["spoonforkbacon","simplestylingsblog","themakerista","younghouselove","simplydesigning","pollythrivinghomeblog","withthegrains","jenna_burger","happymoneysaver","thekitchn"],"hashtags":["healthyfood","easymeal","holiday","frigidairegallery","recipe","baking","pistachio","thekitchn","brie","fallrecipes"]},{"_id":{"$oid":"5aa104e0f20e84e6104ced6c"},"id":"2032147137","type":"add","username":"pugcostumes","bio":"😍😍😍\nTag @pugcostumes for a chance to be featured!\n.\nOur new pug entertainment website","followed_by":33627,"mentions":["peeweesbigpugventure","homerpugalicious","thebatmanpug","lojapetitgato","russell_the_pug","its.louis.the.pug","pugsloveronly","pippsthepug","insitu","pug_a_frenchie_and_brian"],"hashtags":["tacosandtequila","tacos🌮","tacos","pugcostume","dogcostume","pug","tacotuesday","halloween","pugtalk","puginterview"]},{"_id":{"$oid":"5aa104e0f20e84e6104ced6d"},"id":"2240837209","type":"add","username":"_ericgorman","bio":"","followed_by":259,"mentions":["seltzer_cat"],"hashtags":["kansascitychiefs","mediacircus","hairgoals","mynypd","pastaface","rabbisanta"]},{"_id":{"$oid":"5aa104e0f20e84e6104ced6e"},"id":"2535125900","type":"add","username":"ciadotiojoao","bio":"Sua melhor cia!\n3028-3329 / 9 9299-2909\nPeça já seu orçamento.","followed_by":816,"mentions":["ciadotiojoao","fernandarosafloresboutique","lezanfan","eduarda_peixoto","ciadacriancars","minhafestapoa"],"hashtags":["praia","ciadotiojoao","summer","ferias","feliznatal","minhafestapoa","ciadotiojoao🍫🍓","vemverão","excelência","boacia"]},{"_id":{"$oid":"5aa104e0f20e84e6104ced6f"},"id":"20263510","type":"add","username":"dontcarebear","bio":"everything is everything (photos of rescue pomeranians, performance, rock n roll, cats, and the infinitesimal)","followed_by":699,"mentions":["1234gorecords","jerkofalltrades","studsf","michelenet","knitandresist","dani_of_pts","lil_cattyshack","muttvillesf","dumbtattoo","deeleitmakeup"],"hashtags":["muttvillealum","pomeranian","julieruinthepom","rescuepom","🐻","thecoverups","soldoutshow","sobersally","ivyroomalbany","kickdrum"]},{"_id":{"$oid":"5aa104e0f20e84e6104ced70"},"id":"202504227","type":"add","username":"dexterkane","bio":"www.shadowsanctuary.com","followed_by":2113,"mentions":["thoma106","phonicarecords","kristinarecords","djmagofficial","otilia_marques","wearesoundspace","dissonance909","zephyr_restaurant_bar","tombulwer","fybe.one"],"hashtags":["soundhire","avrentals","savefabric"]},{"_id":{"$oid":"5aa104e0f20e84e6104ced71"},"id":"202245203","type":"add","username":"jruncio","bio":"CAPITAL","followed_by":530,"mentions":["e_a_ferguson","romeryounggallery","christopherebaird","rainenk","_c_a_p_i_t_a_l_","cindycindy123","studioeyeneye","mcliffordgreen","thethingquarterly","themoderninstitute"],"hashtags":["listeningwithleon","johanson","mood","wedeliverartforbacon","jbar","ot","aliciamccarthy","davinasemo","williamsburroughs","rainenknecht"]},{"_id":{"$oid":"5aa104e0f20e84e6104ced72"},"id":"1675287336","type":"add","username":"_dame_dt","bio":"God 1st! 29 yrs old Blessed and loving My Journey! 🙏LIVE LOVE LIFE!  #PROSPER STAY HUMBLE AND NO EXCUSES! #THANKFUL UPLIFT!  973 ✈ 704 Stay blessed!","followed_by":2805,"mentions":["angie_pangie2","osonarley","beautifully_dyanab","trautogroup","laterra2","capos__world","dames_den","bsfnigeria","edjaacate","branded_xpressions"],"hashtags":["ciaa2018","ciaaweekend","ciaa","charlotte","704","queencity","family","epic","hailstate","mood"]},{"_id":{"$oid":"5aa104e0f20e84e6104ced73"},"id":"30282226","type":"add","username":"carmenleung1","bio":"24 / Sydney / W.B & 🐶\n@performance.ep_carmen","followed_by":612,"mentions":["dan_ferris3","bassamalam","breakthroughfitness_","climbfit_sydney","missyandme_photos","willbandian","performancecoach_wilmot","vesnizzle","athletesauthority","performance.ep_carmen"],"hashtags":["strathfield","exercise","rehab","rehabilitation","innerwest","physiotherapy","exercisephysiology","functionaltraining","sydney","getawayfromme"]},{"_id":{"$oid":"5aa104e0f20e84e6104ced74"},"id":"2008676241","type":"add","username":"weshakespeare","bio":"Shut up and create 🔈🎶 // Follow us on Twitter: @WeShakespeare // Subscribe to our Soundcloud","followed_by":8383,"mentions":["justinbieber","syd","4mamaearth","wale","commonkings","jordan_fisher","theinternet","amoebahollywood","jimmyfallon","annalemusic"],"hashtags":["picoftheday","look","hiphop","songwriter","tweegram","smile","hiphopmusic","tuesdaytruth","love","nowplaying"]},{"_id":{"$oid":"5aa104e0f20e84e6104ced75"},"id":"606501473","type":"add","username":"danilojaris","bio":"Eng.Mecenica⚙️. Biemex rider Jaris.26\nBike mai que tudo🚲.👻danilojaris.","followed_by":1048,"mentions":["gabrelfernandofilms","matheus_cesar_","biielbmx","ratatuibmx","toycanola","rodrigo_bm_silva","orleanac","gs_henrique","gabrielcamargobmx","caiquesiqueiraa_"],"hashtags":["bmx","indaiatuba","vertical","vertbrasil","street","jarinu","nqm","roledeontem","malokatricke","ladeirabaixo"]},{"_id":{"$oid":"5aa104e0f20e84e6104ced76"},"id":"1202284430","type":"add","username":"queenzanayyaramakaila","bio":"","followed_by":855,"mentions":["tulababycarriers","zakkelbabycarriers","pangeranlubis02","thenest.babywrap","chaiirunnisaa_ummunaziha","annie_lovina","sricicie","gendong.id","vy_siregar","banjarmasin.babywearers"],"hashtags":["kopdarke15medanbabywearers","gendonganbayi","littleforestgiveaway","yogyakarta","ringslings","wovenwrapindonesia","gendongan","komunitasmenggendong","babywearing","babycarrier"]},{"_id":{"$oid":"5aa104e0f20e84e6104ced77"},"id":"4543538733","type":"add","username":"nataliejordan.b","bio":"Inbetweener ✨ Frank Model Management 📍 LA","followed_by":934,"mentions":["its_christian","rachellkang","tyrabanks","frankmodelmanagement","syldon","bbarreto","demireeves","bellaagolden","allieeayers","ashleyseryn"],"hashtags":["tgif","inbetweeners","bodypositive","film","beachphotography","newfacemodel","blondehair","blondie","socal","goldenhour"]},{"_id":{"$oid":"5aa104e0f20e84e6104ced78"},"id":"2004067193","type":"add","username":"besttimeevernph","bio":"The official Instagram for #BestTimeEver.","followed_by":20054,"mentions":["mattlauernbc","omi","mrsilverscott","meredithvieira","queenofthenightnyc","reba","nph","penelopebofficial","shaq","savannahguthrie"],"hashtags":["besttimeever","howinevermetyourmother","bsbonbtesweepstakes","🎃","halloweenbtesweepstakes","wcw","littleshaq","mondaymotivation"]},{"_id":{"$oid":"5aa104e0f20e84e6104ced79"},"id":"2001081763","type":"add","username":"doglife_skt","bio":"DOGLIFE Skate, Skills, Vivencia!","followed_by":295,"mentions":["flipagirls_","ue_will","caiovieiraskt","rafael_car","adam_paneto","biihelena","cbskateshop","doglife_skt","dermeribeiro","90skateshop"],"hashtags":["poucas","doglife","largaosbracos","butanclan","skaterua","uniskt","skatesalva","skatelife","sofoi","skills"]},{"_id":{"$oid":"5aa104e0f20e84e6104ced7a"},"id":"2018915478","type":"add","username":"jacobhacklany","bio":"Wedding and Events Planner | Master of Ceremonies | Singer \n📞  0451440477 \n📧  info@jacobhacklany.com.au","followed_by":7401,"mentions":["mrjayson","michaelarthurdiamonds","amandasbakehouse","artistryco_bytiav","allanayounan","jesselchei","sydneyexoticcarhire","the_ella_group","xsightphotography","forevermarried"],"hashtags":["weddedwonderland","happilyeverafter","grandweddings","luxewedding","dreamday","bride","weddingcake","love","groom","jacobhacklany"]},{"_id":{"$oid":"5aa104e0f20e84e6104ced7b"},"id":"1997605964","type":"add","username":"amirhossein_allahyari","bio":"الكتاب، عقاب قله يوشان ، ان حرف دگر، تنها اين را براي تو نوشته ام مريم، چشمهاي قهوه اي تو، پري خواني، سلام بر حيدربابا، سلامت در شاهنامه","followed_by":2009,"mentions":["hamedpix","peyman.mosalli","mortezaatousi","sbiabanaki","saeed.naghavi.bb","alireza_bandari","linda.berenji","kiawasch"],"hashtags":["شبانه","به_سوي_كرمانشاه","موت_صغير","عين_القضات","علي","سيد_خليل","مولوي","شمس","عالي_نژاد","خوب"]},{"_id":{"$oid":"5aa104e0f20e84e6104ced7c"},"id":"198244173","type":"add","username":"jordanxbell","bio":"St. Louis | ⚾️ Thirdbase ®","followed_by":5134,"mentions":["40wop","maisey_rogers","im_positively_splash","bigblack_thedon","que_berry23","magnuspanther","braxattacks","kd_gray","leonardo.chop","jaylonsmith"],"hashtags":["lostinaminute","tbt"]},{"_id":{"$oid":"5aa104e0f20e84e6104ced7d"},"id":"197816389","type":"add","username":"chachadumdum","bio":"📍Shop Barra 71 3264-4214\n📍Shop da Bahia 71 3450-4416\n📍Shop Bela Vista 71 3431-5153\nSAC: chachadumdum@hotmail.com WhatsApp7199197-0708","followed_by":20919,"mentions":["tiagotquirino86","gbamor","lianaramos","vitorjrfisio","vitorhugoabreuu","peeeu09","loriivianna","cauramos","igornovack","eusoufilipemiranda"],"hashtags":["chachadumdum","shoppingbelavista","shoppingdabahia","shoppingbarra","shoppingdabahiaoficial","fé","festadeyemanjá","diadeyemanjá","yemanjá","chacha"]},{"_id":{"$oid":"5aa104e0f20e84e6104ced7e"},"id":"196830165","type":"add","username":"raecliff","bio":"Elite🇨🇦 Distance Runner | 2017 IAAF World Champs | BCEP | Olympic Hopeful | UBC Research Assistant | MSc Occupational & Environmental Hygiene |","followed_by":1544,"mentions":["nancy.cliff","pbchocolatemilk","chevronhoustonmarathon","alnbrookes","_chrisyu","chriswinter2","whistler50","ronald_cliff","bcendurance","thewoodlandsmarathon"],"hashtags":["bcep","pbcm","nuunelite","woodlandshalfmarathon","houston","bcathletics","canadianrunning","vancitystorm","thankscoach","pacificspiritpark"]},{"_id":{"$oid":"5aa104e0f20e84e6104ced7f"},"id":"1967005466","type":"add","username":"salon_de_stella","bio":"グルーデコ®︎認定講師、EPJDレザーデコ認定講師、ドールチャームレッスン、レザーストラップデコレーション。レッスン、オーダーにつきましてはダイレクトメールよりお気軽にお問い合わせくださいませ。webショップ ★ https://stelladoll.thebase.in","followed_by":331,"mentions":["lamaturite_m","salon_de_stella","shigechanfarm","asamimilii","etoile1130","mitsu_ustim0717","kinuya_cosmetic","mariesselection2","rose_._tara","get_repost"],"hashtags":["キンカンの甘露煮","喉にいい","滋賀グルーデコ","サロンドステラ","グルーデコ","salondestella","初めて作りました","黒猫ちゃんも作ってみたい","fairy","新作"]},{"_id":{"$oid":"5aa104e0f20e84e6104ced80"},"id":"1959706087","type":"add","username":"championsportsperformance","bio":"Champion Sports Performance helps athletes develop speed and agility to perform at their best and build a competitive edge.","followed_by":286,"mentions":["bburns229","advantagestrength","coachphilhueston","joepowell28","houghtz","coachwalker29","mikevorkapich","stabilityes","smarterteamtraining","rmckeefery"],"hashtags":["bsstandsforbrainstorm","brainstormoftheday","winwin","bsotd","baseball","peshbaseball","athletic","softball","buildingchampions","getup"]},{"_id":{"$oid":"5aa104e0f20e84e6104ced81"},"id":"195755344","type":"add","username":"nakedinthewild","bio":"You don't have to choose between being a lady and being tough. Tahoe girl. ૐ // Enter my snø cät giveaway here!","followed_by":25487,"mentions":["ojoemarshall","iamspecialized_mtb","mattspadi","tahoetimber","spyoptic","redingtongear","bts_nakedinthewild","carvedesigns","tehsager","nomadboutique"],"hashtags":["outdoorwomen","laketahoe","powderday","skiing","freealpine","tugisthedrug","girlswhofish","flyfishing","flytying","flytyingmonth2018"]},{"_id":{"$oid":"5aa104e0f20e84e6104ced82"},"id":"195355324","type":"add","username":"aleolak","bio":"from Poland\nkkalexandrakk@gmail.com","followed_by":7771,"mentions":["upagainstthewall","jorya_xinhee","asus","annadyszkiewicz","wandareignonthebund","davemasotti","chloevocalist","fabiobozzetti","maximvdnphoto","makeup_marco"],"hashtags":["adrnight","backstage","aftercroissantsinbed","lovemilan","notawinterperson","needsun","icantseeshit","paperinmyeyes","shanghai","shanghaitower"]},{"_id":{"$oid":"5aa104e0f20e84e6104ced83"},"id":"4013559231","type":"add","username":"ahc_brittany","bio":"Brittany \nAtlanta Hawks Cheerleader| True to Atlanta | 2nd Season","followed_by":561,"mentions":["ahc_kimberly","house_of_akd","ahc_jennifer","proaction","eriebayhawks","bayhawksdanceteam","ahc__brittanyz","fox5atlanta","proactiondance","11alive"],"hashtags":["truetoatlanta","atlhawks","atlhawkscheer","nbadancers","nsync","friday","proactiondance","nba","dirtypop","philipsarena"]},{"_id":{"$oid":"5aa104e0f20e84e6104ced84"},"id":"2159382520","type":"add","username":"mnmvzla","bio":"Febrero 2018\nTeatro Baralt de Maracaibo.\nHomenaje al Rey del Pop.","followed_by":2829,"mentions":["get_repost","symproducciones","repostit_app","teatrobarelalt","teatrobarlt","zendcreativestudio","sistemazulia","mnmvzla","abdiasant","katvielma"],"hashtags":["pop","michaeljackson","cantantes","rock","rockwithyou","music","sinfónico","maracaibo","11oct","littlesussie"]},{"_id":{"$oid":"5aa104e0f20e84e6104ced85"},"id":"1940083831","type":"add","username":"rivaldiways","bio":"From far away \nDaydreamer\nOn sale\nDiario de antonia","followed_by":396,"mentions":["mazizotorres","aaragimenez","juancarotela","abelchogonzalez","jorgedanielcacerescenturion","amadosarabia","pablo_corrales01","juanmi_leguizamon","danielaasu","pablo_daniel019"],"hashtags":["eldiariodeantonia","apologiaalainmadurez","riopirareta","lleganavidadyyosinti","feminasdelrock","grabanding","demo","probanding","90","largavidaalrock"]},{"_id":{"$oid":"5aa104e0f20e84e6104ced86"},"id":"2159299881","type":"add","username":"lashesbymai_","bio":"Located in Boston's historic North End, specializing in eyelash extensions. ✉️lashesbymai@gmail.com","followed_by":1945,"mentions":[],"hashtags":["bostonmagazine","eyelashesfordays","bostoneyelashes","bostonspa","lashesfordays","improperbostonian","bossbabes","bostonbrides","bostonmua","bostonmakeupartist"]},{"_id":{"$oid":"5aa104e0f20e84e6104ced87"},"id":"419862848","type":"add","username":"skinnybites","bio":"","followed_by":6,"mentions":[],"hashtags":[]},{"_id":{"$oid":"5aa104e0f20e84e6104ced88"},"id":"6235669866","type":"add","username":"nonlaburger","bio":"Call us today! (269) 443-2270\nWe're looking forward to seeing you next!\n📍2103 S. Burdick St. Kalamazoo, MI 49001\nHours: 11:30a-8:30p Tues-Sat","followed_by":1424,"mentions":["mlivenews","nonlaburger.com"],"hashtags":["cheesecake","discoverkzoo","basquestyle","dulcedeleche","realfoodrealtaste","puremichigan","chefspecial","nonlaburger","dessert","kalamazoo"]},{"_id":{"$oid":"5aa104e0f20e84e6104ced89"},"id":"19351770","type":"add","username":"cafesmalongo","bio":"Premier intervenant des cafés issus du commerce équitable et de l’agriculture biologique, Malongo est le spécialiste français des cafés haut de gamme.","followed_by":2034,"mentions":["th.louis","fringeandfrange","ruedeseglantines_","ceciliaschnickschnack","francebleuazur","mespetitespaillettes","afireclouds","lifepastryclem","grabirelle","parisianlifebylea"],"hashtags":["malongo","cafésmalongo","café","coffee","cafe","latteart","paris","concoursjpc2018","saintvalentin","valentinesday"]},{"_id":{"$oid":"5aa104e0f20e84e6104ced8a"},"id":"193412847","type":"add","username":"convictionsrock","bio":"On tour with War Of Ages.\n\"I Will Become\" is out now.\n• 👇🏻MERCH STORE 👇🏻 •","followed_by":48388,"mentions":["fitforakingtx","ryankirbz","lmtf","abrband","damonstrosity","warofages","zachariahmayfield","joshconvictions","convictionsrock","darknessdividedband"],"hashtags":["thealphatour","convictionsrock","warofages","earthgroans","aggressiveworship","alphatour","2"]},{"_id":{"$oid":"5aa104e0f20e84e6104ced8b"},"id":"1931736748","type":"add","username":"marys_sweets_","bio":"🌟Новосибирск\n🍰Капкейки🎂торты🍧десерты в стаканчиках🍓клубника в шоколаде\n🎨индивидуальный дизайн \n⏰срочные заказы \n👉WhatsApp +7(909-42-31-468)👈\n🌸Мария","followed_by":13761,"mentions":["gennadii4615","mary_kirillovich","eurosweet_nsk","parfumica.ru","marys_sweets_"],"hashtags":["капкейкинск","сладостинск","тортынск","cakes","капкейкиназаказ","тортнск","макаруны","тортыспб","кексы","выпечканск"]},{"_id":{"$oid":"5aa104e0f20e84e6104ced8c"},"id":"231770565","type":"add","username":"kevinogar","bio":"Owner of CrossFit WatchTower - CrossFit L1 Staff - CrossFit Specialty Course: Adaptive Training Staff. \nhttps://www.progenexusa.com/?share=PRGNXELT45","followed_by":46325,"mentions":["b_n_d_k","xoambam","bodybuildingcom","compexusa","addressandattack","romwod","thejimmcd","fathomcrossfit","spencernix","iamunscared"],"hashtags":["thejournal","wheelwodnation","crossfitjournal","adaptivecrossfit","wheelwod","adaptivetraining","signupforacourseandhearsomewheeliebadjokes","repost","crossfitisforeveryone","adaptiveopen"]},{"_id":{"$oid":"5aa104e0f20e84e6104ced8d"},"id":"1912215266","type":"add","username":"lesvieuxsinges","bio":"","followed_by":726,"mentions":[],"hashtags":[]},{"_id":{"$oid":"5aa104e0f20e84e6104ced8e"},"id":"2282252914","type":"add","username":"wolfofyachting","bio":"🔷Yachting Lifestyle Influencer \n🔹Based in South Florida\n🔹Established 2015\n🔷DM Business Inquires\\Promo Rates 📥","followed_by":93020,"mentions":["fiskerinc","benettiyachtsofficial","stephsandiland","gabriellecjm_","uncovermiami","vvcastrillon","mercedesbenz","brendan_butler","marktheshark","topyacht"],"hashtags":["carsofinstagram","instagram","goodlife","yachting","lambo","luxuryyacht","luxuries","wealth","lifestyletop","sv"]},{"_id":{"$oid":"5aa104e0f20e84e6104ced8f"},"id":"1828528363","type":"add","username":"inspirasian_food_truck","bio":"","followed_by":316,"mentions":[],"hashtags":["arepaslasgorditas","bunzaitruck","lizziessweetcreations","asaostruck","bang"]},{"_id":{"$oid":"5aa104e0f20e84e6104ced90"},"id":"190630221","type":"add","username":"alexadaysilva","bio":"BK —> ATX Designer @outdoorvoices","followed_by":961,"mentions":["pictureroomnyc","heavy.set","z_and_trumpets","lillianhardy","alexsteckly","brookedidonato","outdoorvoices","snakefox___","blanca____________","andybeam"],"hashtags":["doingthings","blessed","believeland","tbt","kentreunion","ivoted","imwithelasticwaistbands","imwithdonuts","imwithher","vote"]},{"_id":{"$oid":"5aa104e0f20e84e6104ced91"},"id":"1383623611","type":"add","username":"hemoceoficial","bio":"Av. José Bastos, 3390, Rodolfo Teófilo\nHorário de funcionamento\nSegunda a sexta: 7h30min às 18h30min\nSábados: 8h às 16h","followed_by":6539,"mentions":[],"hashtags":["doevida","vidasquesalvamvidas","hemoce","doesangue","diainternacionaldamulhernohemoce","doesanguenohemoce","suamelhorparte","doeplaquetas","sejasolidário","carnavaldohemoce"]},{"_id":{"$oid":"5aa104e0f20e84e6104ced92"},"id":"1900355339","type":"add","username":"clubcocoonasaba","bio":"3 Ogochukwu Moweta, Off Summit/Dla Road Asaba Delta State ..Table Booking & Enquires - 08039480995..","followed_by":1197,"mentions":["realangelaokorie","ocean","babarex01","ocean_peterson","iceprincezamani","dgeemusic","randy_wanye","kingfessa.b.okafor","randy_wayne"],"hashtags":["31savage","succesful","halloweenparty","premiumnightlife","onlyforthesocialbutterflies","asabaparty","clubcocoonasaba","turnup","teamclassic","teampepperdemwithtatashe"]}]
